takeme_openpyxl/__init__.py
takeme_openpyxl/reader/__init__.py
takeme_openpyxl/writer/__init__.py
takeme_openpyxl-1.0.3.dist-info/LICENSE
takeme_openpyxl-1.0.3.dist-info/METADATA
takeme_openpyxl-1.0.3.dist-info/WHEEL
takeme_openpyxl-1.0.3.dist-info/top_level.txt
takeme_openpyxl-1.0.3.dist-info/RECORD
