Metadata-Version: 2.1
Name: takeme-openpyxl
Version: 1.0.3
Summary: Python Wrapper for openpyxl
Home-page: https://github.com/takeme-pay/openpyxl
Author: Yukitaka Maeda
Author-email: yukitaka.maeda@takeme.com
License: GPLv3+
Keywords: openpyxl excel TakeMe
Platform: any
Classifier: Programming Language :: Python
Classifier: Programming Language :: Python :: 3
Requires-Dist: openpyxl
